Metadata-Version: 1.1
Name: doopla
Version: 0.3.0
Summary: A Python script to fetch the output of fail tasks from ours Hadoop clusters
Home-page: https://github.com/trustyou/doopla
Author: Miguel Cabrera
Author-email: mfcabrera@gmail.com
License: Copyright 2015 Miguel Cabrera
